ezselenium
