Metadata-Version: 1.1
Name: ezselenium
Version: 0.1.5
Summary: Common selenium functions
Home-page: https://github.com/benbrunyee/ezselenium
Author: Ben Brunyee
Author-email: brunyeeb@gmail.com
License: UNKNOWN
Platform: UNKNOWN
Classifier: Development Status :: 3 - Alpha
Classifier: Intended Audience :: Developers
Classifier: Programming Language :: Python :: 3
Classifier: Programming Language :: Python :: 3.6
Classifier: Programming Language :: Python :: 3.7
Classifier: Programming Language :: Python :: 3.8
Classifier: Programming Language :: Python :: 3.9
